CoAuthorNet/__init__.py
CoAuthorNet/network_analysis.py
CoAuthorNet/visualization.py
CoAuthorNet-0.2.0.dist-info/LICENSE
CoAuthorNet-0.2.0.dist-info/METADATA
CoAuthorNet-0.2.0.dist-info/WHEEL
CoAuthorNet-0.2.0.dist-info/top_level.txt
CoAuthorNet-0.2.0.dist-info/RECORD
