Metadata-Version: 2.1
Name: CoAuthorNet
Version: 0.2.0
Summary: A package for analyzing and visualizing university authorship networks
Home-page: https://github.com/nathaninkiriwang/CoAuthorNet
Author: Nathan Inkiriwang, Bryan Ng
Author-email: nathan.inkiriwang@sydney.edu.au, yizhe.ng@sydney.edu.au
Classifier: Programming Language :: Python :: 3
Classifier: License :: OSI Approved :: MIT License
Classifier: Operating System :: OS Independent
Requires-Python: >=3.6
License-File: LICENSE
Requires-Dist: pandas
Requires-Dist: networkx
Requires-Dist: numpy
Requires-Dist: matplotlib
Requires-Dist: tqdm
Requires-Dist: scholarly
